pydantic_fire/__init__.py
pydantic_fire/schema_manager.py
pydantic_fire/async_operations/async_base.py
pydantic_fire/async_operations/async_decorators.py
pydantic_fire/async_operations/async_transactions.py
pydantic_fire/common/__init__.py
pydantic_fire/common/decorators.py
pydantic_fire/core/__init__.py
pydantic_fire/core/base.py
pydantic_fire/core/exceptions.py
pydantic_fire/core/fields.py
pydantic_fire/core/types.py
pydantic_fire/gateway/async_gateway.py
pydantic_fire/gateway/base_gateway.py
pydantic_fire/gateway/exceptions.py
pydantic_fire/gateway/sync_gateway.py
pydantic_fire/sync_operations/decorators.py
pydantic_fire/sync_operations/transactions.py
pydantic_fire/templates/base_rules.template
pydantic_fire/templates/collection_rules.template
pydantic_fire/templates/field_validation.template
pydantic_fire/tests/__init__.py
pydantic_fire/tests/async_mocks.py
pydantic_fire/tests/mocks.py
pydantic_fire/tests/test_async_decorators.py
pydantic_fire/tests/test_async_gateway.py
pydantic_fire/tests/test_async_transactions.py
pydantic_fire/tests/test_base.py
pydantic_fire/tests/test_common_decorators.py
pydantic_fire/tests/test_core.py
pydantic_fire/tests/test_sync_decorators.py
pydantic_fire/tests/test_sync_gateway.py
pydantic_fire/tests/testing.py
pydantic_fire/utils/docs_generator.py
pydantic_fire/utils/emulator.py
pydantic_fire/utils/introspection.py
pydantic_fire/utils/rules_generator.py
pydantic_fire/utils/visualization.py
pydantic_fire-1.0.2.dist-info/licenses/LICENSE
pydantic_fire-1.0.2.dist-info/METADATA
pydantic_fire-1.0.2.dist-info/WHEEL
pydantic_fire-1.0.2.dist-info/top_level.txt
pydantic_fire-1.0.2.dist-info/RECORD
